vidkompy/__init__.py
vidkompy/__main__.py
vidkompy/__version__.py
vidkompy/models.py
vidkompy/vidkompy.py
vidkompy/core/__init__.py
vidkompy/core/alignment_engine.py
vidkompy/core/dtw_aligner.py
vidkompy/core/frame_fingerprint.py
vidkompy/core/multi_resolution_aligner.py
vidkompy/core/numba_optimizations.py
vidkompy/core/precise_temporal_alignment.py
vidkompy/core/spatial_alignment.py
vidkompy/core/temporal_alignment.py
vidkompy/core/tunnel_aligner.py
vidkompy/core/video_processor.py
vidkompy-1.2.5.dist-info/METADATA
vidkompy-1.2.5.dist-info/WHEEL
vidkompy-1.2.5.dist-info/licenses/LICENSE
vidkompy-1.2.5.dist-info/RECORD
