Metadata-Version: 2.4
Name: vidkompy
Version: 1.2.5
Project-URL: Documentation, https://github.com/twardoch/vidkompy#readme
Project-URL: Issues, https://github.com/twardoch/vidkompy/issues
Project-URL: Source, https://github.com/twardoch/vidkompy
Author-email: Adam Twardoch <adam+github@twardoch.com>
License-Expression: MIT
License-File: LICENSE
Classifier: Development Status :: 4 - Beta
Classifier: Programming Language :: Python
Classifier: Programming Language :: Python :: 3.10
Classifier: Programming Language :: Python :: 3.11
Classifier: Programming Language :: Python :: 3.12
Classifier: Programming Language :: Python :: Implementation :: CPython
Classifier: Programming Language :: Python :: Implementation :: PyPy
Requires-Python: >=3.10
Requires-Dist: ffmpeg-python
Requires-Dist: fire
Requires-Dist: loguru
Requires-Dist: numba>=0.58.0
Requires-Dist: numpy
Requires-Dist: opencv-contrib-python
Requires-Dist: rich
Requires-Dist: scikit-image
Requires-Dist: scipy
Requires-Dist: soundfile
Provides-Extra: all
Requires-Dist: ffmpeg-python; extra == 'all'
Requires-Dist: fire; extra == 'all'
Requires-Dist: hatch-vcs>=0.3.0; extra == 'all'
Requires-Dist: hatchling>=1.21.0; extra == 'all'
Requires-Dist: loguru; extra == 'all'
Requires-Dist: mypy>=1.0.0; extra == 'all'
Requires-Dist: numpy; extra == 'all'
Requires-Dist: opencv-contrib-python; extra == 'all'
Requires-Dist: pre-commit>=4.2.0; extra == 'all'
Requires-Dist: pytest-cov>=6.1.1; extra == 'all'
Requires-Dist: pytest>=8.3.5; extra == 'all'
Requires-Dist: pyupgrade>=3.19.0; extra == 'all'
Requires-Dist: rich; extra == 'all'
Requires-Dist: ruff>=0.1.0; extra == 'all'
Requires-Dist: scikit-image; extra == 'all'
Requires-Dist: scipy; extra == 'all'
Requires-Dist: soundfile; extra == 'all'
Provides-Extra: dev
Requires-Dist: mypy>=1.0.0; extra == 'dev'
Requires-Dist: pre-commit>=4.2.0; extra == 'dev'
Requires-Dist: pyupgrade>=3.19.0; extra == 'dev'
Requires-Dist: ruff>=0.1.0; extra == 'dev'
Provides-Extra: test
Requires-Dist: pytest-cov>=6.1.1; extra == 'test'
Requires-Dist: pytest>=8.3.5; extra == 'test'
